{
    "ambientocclusion":false,"textures":{"particle":"#crop","groundcrop":"block/_oaf/bv_invisible"},"elements":[
        {"from":[0,-2,0],"to":[16,-1.99,16],"shade":false,"faces":{"up":{"uv":[0,0,16,16],"texture":"#groundcrop"}}},
        {   
            "from":[0.8,-2,8],"to":[15.2,14,8],"rotation":{"origin":[8,8,8],"axis":"y","angle":45,"rescale":true},"shade":false,"faces":{
                "north":{"uv":[ 0, 0,16,16],"texture":"#crop"},
                "south":{"uv":[ 0, 0,16,16],"texture":"#crop"}
            }
        },{
            "from":[8,-2,0.8],"to":[8,14,15.2],"rotation":{"origin":[8,8,8],"axis":"y","angle": 45,"rescale":true},"shade":false,"faces":{
                "west":{"uv":[ 0, 0,16,16],"texture":"#crop"},
                "east":{"uv":[ 0, 0,16,16],"texture":"#crop"}
            }
        }
    ]
}
